[
  {
    "event_type": "Murder",
    "count": 1769
  },
  {
    "event_type": "Accident",
    "count": 1073
  },
  {
    "event_type": "Unknown",
    "count": 2547
  },
  {
    "event_type": "Death",
    "count": 1305
  },
  {
    "event_type": "Supernatural",
    "count": 3004
  },
  {
    "event_type": "Mystery",
    "count": 563
  },
  {
    "event_type": "Violence",
    "count": 346
  },
  {
    "event_type": "Suicide",
    "count": 389
  },
  {
    "event_type": "Natural Disaster",
    "count": 20
  }
]